bugzee_django.py
bugzee_odoo.py
bugzee_client/__init__.py
bugzee_client/client.py
bugzee_client-0.1.1.dist-info/METADATA
bugzee_client-0.1.1.dist-info/WHEEL
bugzee_client-0.1.1.dist-info/top_level.txt
bugzee_client-0.1.1.dist-info/RECORD
