Metadata-Version: 2.4
Name: bugzee-client
Version: 0.1.1
Summary: Bugzee Error Monitoring client libraries
Home-page: https://bugzee.pro
Author: Bugzee Team
Author-email: support@bugzee.pro
Classifier: Development Status :: 4 - Beta
Classifier: Intended Audience :: Developers
Classifier: License :: OSI Approved :: MIT License
Classifier: Programming Language :: Python
Classifier: Programming Language :: Python :: 3
Classifier: Programming Language :: Python :: 3.7
Classifier: Programming Language :: Python :: 3.8
Classifier: Programming Language :: Python :: 3.9
Classifier: Programming Language :: Python :: 3.10
Classifier: Programming Language :: Python :: 3.11
Classifier: Topic :: Software Development
Classifier: Topic :: System :: Monitoring
Requires-Python: >=3.7
Requires-Dist: requests>=2.0.0
Dynamic: author
Dynamic: author-email
Dynamic: classifier
Dynamic: home-page
Dynamic: requires-dist
Dynamic: requires-python
Dynamic: summary
